TWSIBAPI_MODULES/AccountInfo.py
TWSIBAPI_MODULES/Configurations.py
TWSIBAPI_MODULES/Contracts.py
TWSIBAPI_MODULES/DataStreams.py
TWSIBAPI_MODULES/Dataframes.py
TWSIBAPI_MODULES/Exceptions.py
TWSIBAPI_MODULES/Orders.py
TWSIBAPI_MODULES/__init__.py
TWSIBAPI_MODULES/exceptions_handler.py
TWSIBAPI_MODULES/exeptions_handler.py
TWSIBAPI_MODULES/helpers.py
TWSIBAPI_MODULES/utils.py
ibkrtwsapi_modules-0.0.40.dist-info/LICENSE
ibkrtwsapi_modules-0.0.40.dist-info/METADATA
ibkrtwsapi_modules-0.0.40.dist-info/WHEEL
ibkrtwsapi_modules-0.0.40.dist-info/top_level.txt
ibkrtwsapi_modules-0.0.40.dist-info/RECORD
