Metadata-Version: 2.1
Name: ibkrtwsapi-modules
Version: 0.0.40
Summary: Modules for the Interactive Brokers API
Author: Diego Tamayo
Author-email: diegowork2203@gmail.com
License: MIT
Keywords: interactive brokers api
Classifier: Development Status :: 3 - Alpha
Classifier: Intended Audience :: Developers
Classifier: Topic :: Software Development :: Build Tools
Classifier: Programming Language :: Python :: 3.11
License-File: LICENSE
Requires-Dist: ibapi
Requires-Dist: pandas
